pdfmod/__init__.py
pdfmod/pdfmod.py
pdfmod-0.1.5.dist-info/METADATA
pdfmod-0.1.5.dist-info/WHEEL
pdfmod-0.1.5.dist-info/entry_points.txt
pdfmod-0.1.5.dist-info/RECORD
