Metadata-Version: 2.1
Name: pdfmod
Version: 0.1.5
Summary: A tool for PDF file manipulation.
Author: aoout
Author-email: wuz66280@gmail.com
Requires-Python: >=3.7,<4.0
Classifier: Programming Language :: Python :: 3
Classifier: Programming Language :: Python :: 3.7
Classifier: Programming Language :: Python :: 3.8
Classifier: Programming Language :: Python :: 3.9
Classifier: Programming Language :: Python :: 3.10
Classifier: Programming Language :: Python :: 3.11
Classifier: Programming Language :: Python :: 3.12
Classifier: Programming Language :: Python :: 3.13
Requires-Dist: fire (>=0.4.0,<0.5.0)
Requires-Dist: pymupdf (>=1.21.1,<2.0.0)
